oddtts/README.md
oddtts/__init__.py
oddtts/app.py
oddtts/base_tts_driver.py
oddtts/oddtts.py
oddtts/oddtts_config.py
oddtts/oddtts_params.py
oddtts/test.py
oddtts/tts_bert_vits2.py
oddtts/tts_bert_vits2_v2.py
oddtts/tts_chattts.py
oddtts/tts_edge.py
oddtts/tts_odd_gptsovits.py
oddtts/tts_odd_gptsovits3.py
oddtts/docs/README.md
oddtts/docs/oddtts.png
oddtts/resource/ref.txt
oddtts/tests/test_replace_newline.py
oddtts-1.0.2.dist-info/licenses/LICENSE
oddtts-1.0.2.dist-info/METADATA
oddtts-1.0.2.dist-info/WHEEL
oddtts-1.0.2.dist-info/entry_points.txt
oddtts-1.0.2.dist-info/top_level.txt
oddtts-1.0.2.dist-info/RECORD
