Metadata-Version: 2.4
Name: oddtts
Version: 1.0.2
Summary: A TTS API wrapper server
Author-email: Catherine Wei <catherine@oddmeta.com>, Jacky Wei <jacky@oddmeta.com>
License-Expression: MIT
Project-URL: Homepage, https://oddmeta.net/oddtts
Project-URL: Repository, https://github.com/oddmeta/oddtts
Project-URL: Issues, https://github.com/oddmeta/oddtts/issues
Classifier: Programming Language :: Python :: 3
Classifier: Operating System :: OS Independent
Requires-Python: >=3.10
License-File: LICENSE
Requires-Dist: gradio
Requires-Dist: fastapi==0.128.0
Requires-Dist: uvicorn
Requires-Dist: asyncio
Requires-Dist: edge_tts
Dynamic: license-file
